{
    "variants": {
        "axis=y,up=false,down=false,age=0,waterlogged=false": { "model": "stairway:block/pilar_end_cobble_outer_small",                     "uvlock": true },
        "axis=y,up=false,down=true,age=0,waterlogged=false":  { "model": "stairway:block/pilar_end_cobble_upper_small",                     "uvlock": true },
        "axis=y,up=true,down=false,age=0,waterlogged=false":  { "model": "stairway:block/pilar_end_cobble_lower_small",                     "uvlock": true },
        "axis=y,up=true,down=true,age=0,waterlogged=false":   { "model": "stairway:block/pilar_end_cobble_inner_small",                     "uvlock": true },
        "axis=z,up=false,down=false,age=0,waterlogged=false": { "model": "stairway:block/pilar_end_cobble_outer_small", "x":  90,           "uvlock": true },
        "axis=z,up=false,down=true,age=0,waterlogged=false":  { "model": "stairway:block/pilar_end_cobble_upper_small", "x":  90,           "uvlock": true },
        "axis=z,up=true,down=false,age=0,waterlogged=false":  { "model": "stairway:block/pilar_end_cobble_lower_small", "x":  90,           "uvlock": true },
        "axis=z,up=true,down=true,age=0,waterlogged=false":   { "model": "stairway:block/pilar_end_cobble_inner_small", "x":  90,           "uvlock": true },
        "axis=x,up=false,down=false,age=0,waterlogged=false": { "model": "stairway:block/pilar_end_cobble_outer_small", "x":  90, "y":  90, "uvlock": true },
        "axis=x,up=false,down=true,age=0,waterlogged=false":  { "model": "stairway:block/pilar_end_cobble_upper_small", "x":  90, "y":  90, "uvlock": true },
        "axis=x,up=true,down=false,age=0,waterlogged=false":  { "model": "stairway:block/pilar_end_cobble_lower_small", "x":  90, "y":  90, "uvlock": true },
        "axis=x,up=true,down=true,age=0,waterlogged=false":   { "model": "stairway:block/pilar_end_cobble_inner_small", "x":  90, "y":  90, "uvlock": true },
        "axis=y,up=false,down=false,age=1,waterlogged=false": { "model": "stairway:block/pilar_end_cobble_outer_big",             "y": 270, "uvlock": true },
        "axis=y,up=false,down=true,age=1,waterlogged=false":  { "model": "stairway:block/pilar_end_cobble_upper_big",             "y": 270, "uvlock": true },
        "axis=y,up=true,down=false,age=1,waterlogged=false":  { "model": "stairway:block/pilar_end_cobble_lower_big",             "y": 270, "uvlock": true },
        "axis=y,up=true,down=true,age=1,waterlogged=false":   { "model": "stairway:block/pilar_end_cobble_inner_big",             "y": 270, "uvlock": true },
        "axis=z,up=false,down=false,age=1,waterlogged=false": { "model": "stairway:block/pilar_end_cobble_outer_big",   "x":  90, "y": 180, "uvlock": true },
        "axis=z,up=false,down=true,age=1,waterlogged=false":  { "model": "stairway:block/pilar_end_cobble_lower_big",   "x":  90, "y": 180, "uvlock": true },
        "axis=z,up=true,down=false,age=1,waterlogged=false":  { "model": "stairway:block/pilar_end_cobble_upper_big",   "x":  90, "y": 180, "uvlock": true },
        "axis=z,up=true,down=true,age=1,waterlogged=false":   { "model": "stairway:block/pilar_end_cobble_inner_big",   "x":  90, "y": 180, "uvlock": true },
        "axis=x,up=false,down=false,age=1,waterlogged=false": { "model": "stairway:block/pilar_end_cobble_outer_big",   "x": 270, "y": 270, "uvlock": true },
        "axis=x,up=false,down=true,age=1,waterlogged=false":  { "model": "stairway:block/pilar_end_cobble_upper_big",   "x": 270, "y": 270, "uvlock": true },
        "axis=x,up=true,down=false,age=1,waterlogged=false":  { "model": "stairway:block/pilar_end_cobble_lower_big",   "x": 270, "y": 270, "uvlock": true },
        "axis=x,up=true,down=true,age=1,waterlogged=false":   { "model": "stairway:block/pilar_end_cobble_inner_big",   "x": 270, "y": 270, "uvlock": true },
        "axis=y,up=false,down=false,age=2,waterlogged=false": { "model": "stairway:block/pilar_end_cobble_outer_big",             "y": 180, "uvlock": true },
        "axis=y,up=false,down=true,age=2,waterlogged=false":  { "model": "stairway:block/pilar_end_cobble_upper_big",             "y": 180, "uvlock": true },
        "axis=y,up=true,down=false,age=2,waterlogged=false":  { "model": "stairway:block/pilar_end_cobble_lower_big",             "y": 180, "uvlock": true },
        "axis=y,up=true,down=true,age=2,waterlogged=false":   { "model": "stairway:block/pilar_end_cobble_inner_big",             "y": 180, "uvlock": true },
        "axis=z,up=false,down=false,age=2,waterlogged=false": { "model": "stairway:block/pilar_end_cobble_outer_big",   "x": 270, "y": 180, "uvlock": true },
        "axis=z,up=false,down=true,age=2,waterlogged=false":  { "model": "stairway:block/pilar_end_cobble_upper_big",   "x": 270, "y": 180, "uvlock": true },
        "axis=z,up=true,down=false,age=2,waterlogged=false":  { "model": "stairway:block/pilar_end_cobble_lower_big",   "x": 270, "y": 180, "uvlock": true },
        "axis=z,up=true,down=true,age=2,waterlogged=false":   { "model": "stairway:block/pilar_end_cobble_inner_big",   "x": 270, "y": 180, "uvlock": true },
        "axis=x,up=false,down=false,age=2,waterlogged=false": { "model": "stairway:block/pilar_end_cobble_outer_big",   "x": 270, "y":  90, "uvlock": true },
        "axis=x,up=false,down=true,age=2,waterlogged=false":  { "model": "stairway:block/pilar_end_cobble_lower_big",   "x": 270, "y":  90, "uvlock": true },
        "axis=x,up=true,down=false,age=2,waterlogged=false":  { "model": "stairway:block/pilar_end_cobble_upper_big",   "x": 270, "y":  90, "uvlock": true },
        "axis=x,up=true,down=true,age=2,waterlogged=false":   { "model": "stairway:block/pilar_end_cobble_inner_big",   "x": 270, "y":  90, "uvlock": true },
        "axis=y,up=false,down=false,age=3,waterlogged=false": { "model": "stairway:block/pilar_end_cobble_outer_big",             "y":  90, "uvlock": true },
        "axis=y,up=false,down=true,age=3,waterlogged=false":  { "model": "stairway:block/pilar_end_cobble_upper_big",             "y":  90, "uvlock": true },
        "axis=y,up=true,down=false,age=3,waterlogged=false":  { "model": "stairway:block/pilar_end_cobble_lower_big",             "y":  90, "uvlock": true },
        "axis=y,up=true,down=true,age=3,waterlogged=false":   { "model": "stairway:block/pilar_end_cobble_inner_big",             "y":  90, "uvlock": true },
        "axis=z,up=false,down=false,age=3,waterlogged=false": { "model": "stairway:block/pilar_end_cobble_outer_big",   "x": 270, "y":   0, "uvlock": true },
        "axis=z,up=false,down=true,age=3,waterlogged=false":  { "model": "stairway:block/pilar_end_cobble_lower_big",   "x": 270, "y":   0, "uvlock": true },
        "axis=z,up=true,down=false,age=3,waterlogged=false":  { "model": "stairway:block/pilar_end_cobble_upper_big",   "x": 270, "y":   0, "uvlock": true },
        "axis=z,up=true,down=true,age=3,waterlogged=false":   { "model": "stairway:block/pilar_end_cobble_inner_big",   "x": 270, "y":   0, "uvlock": true },
        "axis=x,up=false,down=false,age=3,waterlogged=false": { "model": "stairway:block/pilar_end_cobble_outer_big",   "x":  90, "y":  90, "uvlock": true },
        "axis=x,up=false,down=true,age=3,waterlogged=false":  { "model": "stairway:block/pilar_end_cobble_upper_big",   "x":  90, "y":  90, "uvlock": true },
        "axis=x,up=true,down=false,age=3,waterlogged=false":  { "model": "stairway:block/pilar_end_cobble_lower_big",   "x":  90, "y":  90, "uvlock": true },
        "axis=x,up=true,down=true,age=3,waterlogged=false":   { "model": "stairway:block/pilar_end_cobble_inner_big",   "x":  90, "y":  90, "uvlock": true },
        "axis=y,up=false,down=false,age=4,waterlogged=false": { "model": "stairway:block/pilar_end_cobble_outer_big",                       "uvlock": true },
        "axis=y,up=false,down=true,age=4,waterlogged=false":  { "model": "stairway:block/pilar_end_cobble_upper_big",                       "uvlock": true },
        "axis=y,up=true,down=false,age=4,waterlogged=false":  { "model": "stairway:block/pilar_end_cobble_lower_big",                       "uvlock": true },
        "axis=y,up=true,down=true,age=4,waterlogged=false":   { "model": "stairway:block/pilar_end_cobble_inner_big",                       "uvlock": true },
        "axis=z,up=false,down=false,age=4,waterlogged=false": { "model": "stairway:block/pilar_end_cobble_outer_big",   "x":  90,           "uvlock": true },
        "axis=z,up=false,down=true,age=4,waterlogged=false":  { "model": "stairway:block/pilar_end_cobble_upper_big",   "x":  90,           "uvlock": true },
        "axis=z,up=true,down=false,age=4,waterlogged=false":  { "model": "stairway:block/pilar_end_cobble_lower_big",   "x":  90,           "uvlock": true },
        "axis=z,up=true,down=true,age=4,waterlogged=false":   { "model": "stairway:block/pilar_end_cobble_inner_big",   "x":  90,           "uvlock": true },
        "axis=x,up=false,down=false,age=4,waterlogged=false": { "model": "stairway:block/pilar_end_cobble_outer_big",   "x":  90, "y": 270, "uvlock": true },
        "axis=x,up=false,down=true,age=4,waterlogged=false":  { "model": "stairway:block/pilar_end_cobble_lower_big",   "x":  90, "y": 270, "uvlock": true },
        "axis=x,up=true,down=false,age=4,waterlogged=false":  { "model": "stairway:block/pilar_end_cobble_upper_big",   "x":  90, "y": 270, "uvlock": true },
        "axis=x,up=true,down=true,age=4,waterlogged=false":   { "model": "stairway:block/pilar_end_cobble_inner_big",   "x":  90, "y": 270, "uvlock": true },
        "axis=y,up=false,down=false,age=5,waterlogged=false": { "model": "stairway:block/pilar_end_cobble_outer_small",                     "uvlock": true },
        "axis=y,up=false,down=true,age=5,waterlogged=false":  { "model": "stairway:block/pilar_end_cobble_upper_small",                     "uvlock": true },
        "axis=y,up=true,down=false,age=5,waterlogged=false":  { "model": "stairway:block/pilar_end_cobble_lower_small",                     "uvlock": true },
        "axis=y,up=true,down=true,age=5,waterlogged=false":   { "model": "stairway:block/pilar_end_cobble_inner_small",                     "uvlock": true },
        "axis=z,up=false,down=false,age=5,waterlogged=false": { "model": "stairway:block/pilar_end_cobble_outer_small", "x":  90,           "uvlock": true },
        "axis=z,up=false,down=true,age=5,waterlogged=false":  { "model": "stairway:block/pilar_end_cobble_upper_small", "x":  90,           "uvlock": true },
        "axis=z,up=true,down=false,age=5,waterlogged=false":  { "model": "stairway:block/pilar_end_cobble_lower_small", "x":  90,           "uvlock": true },
        "axis=z,up=true,down=true,age=5,waterlogged=false":   { "model": "stairway:block/pilar_end_cobble_inner_small", "x":  90,           "uvlock": true },
        "axis=x,up=false,down=false,age=5,waterlogged=false": { "model": "stairway:block/pilar_end_cobble_outer_small", "x":  90, "y":  90, "uvlock": true },
        "axis=x,up=false,down=true,age=5,waterlogged=false":  { "model": "stairway:block/pilar_end_cobble_upper_small", "x":  90, "y":  90, "uvlock": true },
        "axis=x,up=true,down=false,age=5,waterlogged=false":  { "model": "stairway:block/pilar_end_cobble_lower_small", "x":  90, "y":  90, "uvlock": true },
        "axis=x,up=true,down=true,age=5,waterlogged=false":   { "model": "stairway:block/pilar_end_cobble_inner_small", "x":  90, "y":  90, "uvlock": true },

        "axis=y,up=false,down=false,age=0,waterlogged=true": { "model": "stairway:block/pilar_end_cobble_outer_small",                     "uvlock": true },
        "axis=y,up=false,down=true,age=0,waterlogged=true":  { "model": "stairway:block/pilar_end_cobble_upper_small",                     "uvlock": true },
        "axis=y,up=true,down=false,age=0,waterlogged=true":  { "model": "stairway:block/pilar_end_cobble_lower_small",                     "uvlock": true },
        "axis=y,up=true,down=true,age=0,waterlogged=true":   { "model": "stairway:block/pilar_end_cobble_inner_small",                     "uvlock": true },
        "axis=z,up=false,down=false,age=0,waterlogged=true": { "model": "stairway:block/pilar_end_cobble_outer_small", "x":  90,           "uvlock": true },
        "axis=z,up=false,down=true,age=0,waterlogged=true":  { "model": "stairway:block/pilar_end_cobble_upper_small", "x":  90,           "uvlock": true },
        "axis=z,up=true,down=false,age=0,waterlogged=true":  { "model": "stairway:block/pilar_end_cobble_lower_small", "x":  90,           "uvlock": true },
        "axis=z,up=true,down=true,age=0,waterlogged=true":   { "model": "stairway:block/pilar_end_cobble_inner_small", "x":  90,           "uvlock": true },
        "axis=x,up=false,down=false,age=0,waterlogged=true": { "model": "stairway:block/pilar_end_cobble_outer_small", "x":  90, "y":  90, "uvlock": true },
        "axis=x,up=false,down=true,age=0,waterlogged=true":  { "model": "stairway:block/pilar_end_cobble_upper_small", "x":  90, "y":  90, "uvlock": true },
        "axis=x,up=true,down=false,age=0,waterlogged=true":  { "model": "stairway:block/pilar_end_cobble_lower_small", "x":  90, "y":  90, "uvlock": true },
        "axis=x,up=true,down=true,age=0,waterlogged=true":   { "model": "stairway:block/pilar_end_cobble_inner_small", "x":  90, "y":  90, "uvlock": true },
        "axis=y,up=false,down=false,age=1,waterlogged=true": { "model": "stairway:block/pilar_end_cobble_outer_big",             "y": 270, "uvlock": true },
        "axis=y,up=false,down=true,age=1,waterlogged=true":  { "model": "stairway:block/pilar_end_cobble_upper_big",             "y": 270, "uvlock": true },
        "axis=y,up=true,down=false,age=1,waterlogged=true":  { "model": "stairway:block/pilar_end_cobble_lower_big",             "y": 270, "uvlock": true },
        "axis=y,up=true,down=true,age=1,waterlogged=true":   { "model": "stairway:block/pilar_end_cobble_inner_big",             "y": 270, "uvlock": true },
        "axis=z,up=false,down=false,age=1,waterlogged=true": { "model": "stairway:block/pilar_end_cobble_outer_big",   "x":  90, "y": 180, "uvlock": true },
        "axis=z,up=false,down=true,age=1,waterlogged=true":  { "model": "stairway:block/pilar_end_cobble_lower_big",   "x":  90, "y": 180, "uvlock": true },
        "axis=z,up=true,down=false,age=1,waterlogged=true":  { "model": "stairway:block/pilar_end_cobble_upper_big",   "x":  90, "y": 180, "uvlock": true },
        "axis=z,up=true,down=true,age=1,waterlogged=true":   { "model": "stairway:block/pilar_end_cobble_inner_big",   "x":  90, "y": 180, "uvlock": true },
        "axis=x,up=false,down=false,age=1,waterlogged=true": { "model": "stairway:block/pilar_end_cobble_outer_big",   "x": 270, "y": 270, "uvlock": true },
        "axis=x,up=false,down=true,age=1,waterlogged=true":  { "model": "stairway:block/pilar_end_cobble_upper_big",   "x": 270, "y": 270, "uvlock": true },
        "axis=x,up=true,down=false,age=1,waterlogged=true":  { "model": "stairway:block/pilar_end_cobble_lower_big",   "x": 270, "y": 270, "uvlock": true },
        "axis=x,up=true,down=true,age=1,waterlogged=true":   { "model": "stairway:block/pilar_end_cobble_inner_big",   "x": 270, "y": 270, "uvlock": true },
        "axis=y,up=false,down=false,age=2,waterlogged=true": { "model": "stairway:block/pilar_end_cobble_outer_big",             "y": 180, "uvlock": true },
        "axis=y,up=false,down=true,age=2,waterlogged=true":  { "model": "stairway:block/pilar_end_cobble_upper_big",             "y": 180, "uvlock": true },
        "axis=y,up=true,down=false,age=2,waterlogged=true":  { "model": "stairway:block/pilar_end_cobble_lower_big",             "y": 180, "uvlock": true },
        "axis=y,up=true,down=true,age=2,waterlogged=true":   { "model": "stairway:block/pilar_end_cobble_inner_big",             "y": 180, "uvlock": true },
        "axis=z,up=false,down=false,age=2,waterlogged=true": { "model": "stairway:block/pilar_end_cobble_outer_big",   "x": 270, "y": 180, "uvlock": true },
        "axis=z,up=false,down=true,age=2,waterlogged=true":  { "model": "stairway:block/pilar_end_cobble_upper_big",   "x": 270, "y": 180, "uvlock": true },
        "axis=z,up=true,down=false,age=2,waterlogged=true":  { "model": "stairway:block/pilar_end_cobble_lower_big",   "x": 270, "y": 180, "uvlock": true },
        "axis=z,up=true,down=true,age=2,waterlogged=true":   { "model": "stairway:block/pilar_end_cobble_inner_big",   "x": 270, "y": 180, "uvlock": true },
        "axis=x,up=false,down=false,age=2,waterlogged=true": { "model": "stairway:block/pilar_end_cobble_outer_big",   "x": 270, "y":  90, "uvlock": true },
        "axis=x,up=false,down=true,age=2,waterlogged=true":  { "model": "stairway:block/pilar_end_cobble_lower_big",   "x": 270, "y":  90, "uvlock": true },
        "axis=x,up=true,down=false,age=2,waterlogged=true":  { "model": "stairway:block/pilar_end_cobble_upper_big",   "x": 270, "y":  90, "uvlock": true },
        "axis=x,up=true,down=true,age=2,waterlogged=true":   { "model": "stairway:block/pilar_end_cobble_inner_big",   "x": 270, "y":  90, "uvlock": true },
        "axis=y,up=false,down=false,age=3,waterlogged=true": { "model": "stairway:block/pilar_end_cobble_outer_big",             "y":  90, "uvlock": true },
        "axis=y,up=false,down=true,age=3,waterlogged=true":  { "model": "stairway:block/pilar_end_cobble_upper_big",             "y":  90, "uvlock": true },
        "axis=y,up=true,down=false,age=3,waterlogged=true":  { "model": "stairway:block/pilar_end_cobble_lower_big",             "y":  90, "uvlock": true },
        "axis=y,up=true,down=true,age=3,waterlogged=true":   { "model": "stairway:block/pilar_end_cobble_inner_big",             "y":  90, "uvlock": true },
        "axis=z,up=false,down=false,age=3,waterlogged=true": { "model": "stairway:block/pilar_end_cobble_outer_big",   "x": 270, "y":   0, "uvlock": true },
        "axis=z,up=false,down=true,age=3,waterlogged=true":  { "model": "stairway:block/pilar_end_cobble_lower_big",   "x": 270, "y":   0, "uvlock": true },
        "axis=z,up=true,down=false,age=3,waterlogged=true":  { "model": "stairway:block/pilar_end_cobble_upper_big",   "x": 270, "y":   0, "uvlock": true },
        "axis=z,up=true,down=true,age=3,waterlogged=true":   { "model": "stairway:block/pilar_end_cobble_inner_big",   "x": 270, "y":   0, "uvlock": true },
        "axis=x,up=false,down=false,age=3,waterlogged=true": { "model": "stairway:block/pilar_end_cobble_outer_big",   "x":  90, "y":  90, "uvlock": true },
        "axis=x,up=false,down=true,age=3,waterlogged=true":  { "model": "stairway:block/pilar_end_cobble_upper_big",   "x":  90, "y":  90, "uvlock": true },
        "axis=x,up=true,down=false,age=3,waterlogged=true":  { "model": "stairway:block/pilar_end_cobble_lower_big",   "x":  90, "y":  90, "uvlock": true },
        "axis=x,up=true,down=true,age=3,waterlogged=true":   { "model": "stairway:block/pilar_end_cobble_inner_big",   "x":  90, "y":  90, "uvlock": true },
        "axis=y,up=false,down=false,age=4,waterlogged=true": { "model": "stairway:block/pilar_end_cobble_outer_big",                       "uvlock": true },
        "axis=y,up=false,down=true,age=4,waterlogged=true":  { "model": "stairway:block/pilar_end_cobble_upper_big",                       "uvlock": true },
        "axis=y,up=true,down=false,age=4,waterlogged=true":  { "model": "stairway:block/pilar_end_cobble_lower_big",                       "uvlock": true },
        "axis=y,up=true,down=true,age=4,waterlogged=true":   { "model": "stairway:block/pilar_end_cobble_inner_big",                       "uvlock": true },
        "axis=z,up=false,down=false,age=4,waterlogged=true": { "model": "stairway:block/pilar_end_cobble_outer_big",   "x":  90,           "uvlock": true },
        "axis=z,up=false,down=true,age=4,waterlogged=true":  { "model": "stairway:block/pilar_end_cobble_upper_big",   "x":  90,           "uvlock": true },
        "axis=z,up=true,down=false,age=4,waterlogged=true":  { "model": "stairway:block/pilar_end_cobble_lower_big",   "x":  90,           "uvlock": true },
        "axis=z,up=true,down=true,age=4,waterlogged=true":   { "model": "stairway:block/pilar_end_cobble_inner_big",   "x":  90,           "uvlock": true },
        "axis=x,up=false,down=false,age=4,waterlogged=true": { "model": "stairway:block/pilar_end_cobble_outer_big",   "x":  90, "y": 270, "uvlock": true },
        "axis=x,up=false,down=true,age=4,waterlogged=true":  { "model": "stairway:block/pilar_end_cobble_lower_big",   "x":  90, "y": 270, "uvlock": true },
        "axis=x,up=true,down=false,age=4,waterlogged=true":  { "model": "stairway:block/pilar_end_cobble_upper_big",   "x":  90, "y": 270, "uvlock": true },
        "axis=x,up=true,down=true,age=4,waterlogged=true":   { "model": "stairway:block/pilar_end_cobble_inner_big",   "x":  90, "y": 270, "uvlock": true },
        "axis=y,up=false,down=false,age=5,waterlogged=true": { "model": "stairway:block/pilar_end_cobble_outer_small",                     "uvlock": true },
        "axis=y,up=false,down=true,age=5,waterlogged=true":  { "model": "stairway:block/pilar_end_cobble_upper_small",                     "uvlock": true },
        "axis=y,up=true,down=false,age=5,waterlogged=true":  { "model": "stairway:block/pilar_end_cobble_lower_small",                     "uvlock": true },
        "axis=y,up=true,down=true,age=5,waterlogged=true":   { "model": "stairway:block/pilar_end_cobble_inner_small",                     "uvlock": true },
        "axis=z,up=false,down=false,age=5,waterlogged=true": { "model": "stairway:block/pilar_end_cobble_outer_small", "x":  90,           "uvlock": true },
        "axis=z,up=false,down=true,age=5,waterlogged=true":  { "model": "stairway:block/pilar_end_cobble_upper_small", "x":  90,           "uvlock": true },
        "axis=z,up=true,down=false,age=5,waterlogged=true":  { "model": "stairway:block/pilar_end_cobble_lower_small", "x":  90,           "uvlock": true },
        "axis=z,up=true,down=true,age=5,waterlogged=true":   { "model": "stairway:block/pilar_end_cobble_inner_small", "x":  90,           "uvlock": true },
        "axis=x,up=false,down=false,age=5,waterlogged=true": { "model": "stairway:block/pilar_end_cobble_outer_small", "x":  90, "y":  90, "uvlock": true },
        "axis=x,up=false,down=true,age=5,waterlogged=true":  { "model": "stairway:block/pilar_end_cobble_upper_small", "x":  90, "y":  90, "uvlock": true },
        "axis=x,up=true,down=false,age=5,waterlogged=true":  { "model": "stairway:block/pilar_end_cobble_lower_small", "x":  90, "y":  90, "uvlock": true },
        "axis=x,up=true,down=true,age=5,waterlogged=true":   { "model": "stairway:block/pilar_end_cobble_inner_small", "x":  90, "y":  90, "uvlock": true }
    }
}
